tests/__init__.py
tests/test_radius_conv.py
tidef/__init__.py
tidef/__version__.py
tidef/phase_curve.py
tidef-0.0.2.dist-info/LICENSE
tidef-0.0.2.dist-info/METADATA
tidef-0.0.2.dist-info/WHEEL
tidef-0.0.2.dist-info/top_level.txt
tidef-0.0.2.dist-info/RECORD
