Metadata-Version: 2.1
Name: tidef
Version: 0.0.2
Summary: Package to model the phase curve of tidally deformed planets
Home-page: https://github.com/tundeakins/tidef
Author: Babatunde Akinsanmi
Author-email: tunde.akinsanmi@unige.ch
Classifier: Programming Language :: Python
Classifier: License :: OSI Approved :: MIT License
Classifier: Operating System :: OS Independent
License-File: LICENSE
Requires-Dist: numpy
Requires-Dist: scipy
Requires-Dist: matplotlib
Requires-Dist: batman-package
Requires-Dist: ellc
Provides-Extra: dev
Requires-Dist: pytest >=3.7 ; extra == 'dev'
